scpQCA/__init__.py
scpQCA/main.py
scpQCA-0.1.10.dist-info/LICENSE
scpQCA-0.1.10.dist-info/METADATA
scpQCA-0.1.10.dist-info/WHEEL
scpQCA-0.1.10.dist-info/top_level.txt
scpQCA-0.1.10.dist-info/RECORD
