Metadata-Version: 2.1
Name: scpQCA
Version: 0.1.10
Home-page: https://github.com/Kim-Q/scpQCA
Author: Kim.Q
Author-email: fumanqing@outlook.com
License: Apache 2.0
Platform: all
Classifier: Programming Language :: Python :: 3
Classifier: Operating System :: OS Independent
License-File: LICENSE
Requires-Dist: matplotlib
Requires-Dist: sklearn
